tests/__init__.py
tests/admin.py
tests/forms.py
tests/models.py
tests/serializers.py
tests/settings_base.py
tests/test_settings.py
tests/tests.py
tests/urls.py
tests/post_processor/__init__.py
tests/post_processor/discover_tests.py
tests/post_processor/models.py
tests/post_processor/post_processor_tests.py
tests/post_processor/test_settings.py
tests/test_autodiscover/__init__.py
tests/test_autodiscover/versatileimagefield.py
versatileimagefield/__init__.py
versatileimagefield/apps.py
versatileimagefield/fields.py
versatileimagefield/files.py
versatileimagefield/forms.py
versatileimagefield/image_warmer.py
versatileimagefield/mixins.py
versatileimagefield/placeholder.py
versatileimagefield/registry.py
versatileimagefield/serializers.py
versatileimagefield/settings.py
versatileimagefield/utils.py
versatileimagefield/validators.py
versatileimagefield/versatileimagefield.py
versatileimagefield/widgets.py
versatileimagefield/datastructures/__init__.py
versatileimagefield/datastructures/base.py
versatileimagefield/datastructures/filteredimage.py
versatileimagefield/datastructures/mixins.py
versatileimagefield/datastructures/sizedimage.py
versatileimagefield/processors/__init__.py
versatileimagefield/processors/hashlib_processors.py
versatileimagefield/static/versatileimagefield/css/versatileimagefield-bootstrap3.css
versatileimagefield/static/versatileimagefield/css/versatileimagefield-djangoadmin.css
versatileimagefield/static/versatileimagefield/css/versatileimagefield.css
versatileimagefield/static/versatileimagefield/js/versatileimagefield.js
versatileimagefield/templates/versatileimagefield/forms/widgets/attrs.html
versatileimagefield/templates/versatileimagefield/forms/widgets/versatile_image.html
versatileimagefield/templates/versatileimagefield/forms/widgets/versatile_image_bootstrap.html
django_versatileimagefield-3.1.dist-info/LICENSE
django_versatileimagefield-3.1.dist-info/METADATA
django_versatileimagefield-3.1.dist-info/WHEEL
django_versatileimagefield-3.1.dist-info/top_level.txt
django_versatileimagefield-3.1.dist-info/RECORD
